llm_finetuner/__init__.py
llm_finetuner/merge.py
llm_finetuner/train.py
llm_finetuner/upload.py
llm_finetuner/utils.py
llm_finetuner-0.2.0.dist-info/METADATA
llm_finetuner-0.2.0.dist-info/WHEEL
llm_finetuner-0.2.0.dist-info/top_level.txt
llm_finetuner-0.2.0.dist-info/RECORD
